roonapi/.soodmsg
roonapi/__init__.py
roonapi/constants.py
roonapi/discovery.py
roonapi/roonapi.py
roonapi/roonapisocket.py
roonapi/soodmessage.py
roonapi-0.1.5.dist-info/LICENSE
roonapi-0.1.5.dist-info/METADATA
roonapi-0.1.5.dist-info/WHEEL
roonapi-0.1.5.dist-info/RECORD
