Metadata-Version: 2.1
Name: roonapi
Version: 0.1.5
Summary: Provides a python interface to interact with Roon
Home-page: https://github.com/pavoni/pyroon
License: Apache-2.0
Keywords: roon,api
Author: Greg Dowling
Author-email: mail@gregdowling.com
Requires-Python: >=3.7.2,<4.0.0
Classifier: License :: OSI Approved :: Apache Software License
Classifier: Programming Language :: Python :: 3
Classifier: Programming Language :: Python :: 3.8
Classifier: Programming Language :: Python :: 3.9
Classifier: Programming Language :: Python :: 3.10
Classifier: Programming Language :: Python :: 3.11
Requires-Dist: ifaddr (>=0.1.0)
Requires-Dist: requests (>=2.0)
Requires-Dist: six (>=1.10.0)
Requires-Dist: websocket_client (>=1.4.0)
Project-URL: Repository, https://github.com/pavoni/pyroon
